{
    "paragraphs": [
        {
            "id": 1,
            "text": "Parasight is a unique word guessing game designed to challenge your vocabulary and deduction skills. Players are presented with a paragraph where certain words are hidden, and they must use clues to reveal them. The game encourages careful thinking and rewards both knowledge and intuition.",
            "hiddenWords": [
                { "word": "unique", "clue": "One of a kind", "clue2": "Not like anything else", "points": 10 },
                { "word": "challenge", "clue": "A test of ability or skill", "clue2": "Something that puts your abilities to the test", "points": 12 }
            ]
        }
    ]
}
